cf_predict/__init__.py
cf_predict/__main__.py
cf_predict/api.py
cf_predict/config.py
cf_predict/errors.py
cf_predict/resources.py
cf_predict/wsgi.py
cf_predict/test/__init__.py
cf_predict/test/conftest.py
cf_predict/test/test_cf_predict.py
cf_predict-0.1.2.dist-info/DESCRIPTION.rst
cf_predict-0.1.2.dist-info/METADATA
cf_predict-0.1.2.dist-info/RECORD
cf_predict-0.1.2.dist-info/WHEEL
cf_predict-0.1.2.dist-info/entry_points.txt
cf_predict-0.1.2.dist-info/metadata.json
cf_predict-0.1.2.dist-info/top_level.txt
site/__init__.py
tests/__init__.py
tests/conftest.py
tests/test_all.py
