Metadata-Version: 2.0
Name: cf-predict
Version: 0.1.2
Summary: Cloud Foundry Python Predictive API Boilerplate
Home-page: https://github.com/ronert/cf-predict
Author: Ronert Obst
Author-email: ronert.obst@gmail.com
License: MIT
Platform: UNKNOWN
Classifier: Development Status :: 1 - Planning
Classifier: Natural Language :: English
Classifier: Operating System :: OS Independent
Classifier: Programming Language :: Python
Classifier: Programming Language :: Python :: 3.4
Classifier: Programming Language :: Python :: 3.5
Requires-Dist: Flask-RESTful (==0.3.5)
Requires-Dist: Flask-Redis (==0.1.0)
Requires-Dist: mockredispy (==2.9.3)
Requires-Dist: pytest (==2.9.1)
Requires-Dist: pytest-capturelog (==0.7)
Requires-Dist: pytest-cov (==2.2.1)
Requires-Dist: pytest-describe (==0.10.3)
Requires-Dist: pytest-expecter (==0.2.2.post3)
Requires-Dist: pytest-flask (==0.10.0)
Requires-Dist: pytest-random (==0.2)
Requires-Dist: pytest-runfailed (==0.5)
